badidatetime/__init__.py
badidatetime/_astronomical_terms.py
badidatetime/_coefficients.py
badidatetime/_strptime.py
badidatetime/_structures.py
badidatetime/_timedateutils.py
badidatetime/badi_calendar.py
badidatetime/base_calendar.py
badidatetime/datetime.py
badidatetime/gregorian_calendar.py
badidatetime/julian_period.py
badidatetime-0.5.0.dist-info/METADATA
badidatetime-0.5.0.dist-info/WHEEL
badidatetime-0.5.0.dist-info/licenses/LICENSE
badidatetime-0.5.0.dist-info/licenses/LICENSE
badidatetime-0.5.0.dist-info/RECORD
