Metadata-Version: 2.4
Name: badidatetime
Version: 0.5.0
Summary: Badi Calendar Datetime API (badidatetime)
Project-URL: url, https://github.com/cnobile2012/bahai-calendar
Project-URL: Repository, https://github.com/cnobile2012/bahai-calendar
Author-email: "Carl J. Nobile" <carl.nobile@gmail.com>
Maintainer-email: "Carl J. Nobile" <carl.nobile@gmail.com>
License-Expression: MIT
License-File: LICENSE
License-File: LICENSE
Keywords: Badi,Badi Calendar,Badí',Badí' Calendar,Baha'i,Bahá'i,Calendar
Classifier: Development Status :: 4 - Beta
Classifier: Intended Audience :: Developers
Classifier: Operating System :: OS Independent
Classifier: Programming Language :: Python
Classifier: Programming Language :: Python :: 3.10
Classifier: Programming Language :: Python :: 3.11
Classifier: Programming Language :: Python :: 3.12
Classifier: Programming Language :: Python :: 3.13
Requires-Python: >=3.10
Requires-Dist: geocoder
Requires-Dist: tzdata
Requires-Dist: tzlocal
